{
  "name": "K8s Dev Environment",
  "image": "mcr.microsoft.com/devcontainers/base:ubuntu-22.04",
  "features": {
    "ghcr.io/devcontainers/features/docker-in-docker:2": {
      "moby": false
    }
  },
  "postCreateCommand": "curl -s https://raw.githubusercontent.com/k3d-io/k3d/main/install.sh | bash && curl -LO https://dl.k8s.io/release/$(curl -L -s https://dl.k8s.io/release/stable.txt)/bin/linux/amd64/kubectl && chmod +x kubectl && sudo mv kubectl /usr/local/bin/ && curl https://raw.githubusercontent.com/helm/helm/main/scripts/get-helm-3 | bash",
  "forwardPorts": [8080]
}
